README.rst
setup.py
eth_rpc_api/__init__.py
eth_rpc_api/client.py
eth_rpc_api/constants.py
eth_rpc_api/exceptions.py
eth_rpc_api/utils.py
eth_rpc_api.egg-info/PKG-INFO
eth_rpc_api.egg-info/SOURCES.txt
eth_rpc_api.egg-info/dependency_links.txt
eth_rpc_api.egg-info/requires.txt
eth_rpc_api.egg-info/top_level.txt