Metadata-Version: 1.0
Name: eth-rpc-api
Version: 0.3.10
Summary: Ethereum JSON-RPC client
Home-page: https://github.com/sl4mmer/eth_rpc_api
Author: Dead Possum Labs (forked fromn Consensus)
Author-email: info@consensys.net, d.soldatenko@dplabs.irish 
License: MIT
Platform: UNKNOWN
